netifaces.cp36-win_amd64.pyd
netifaces_w38-0.10.9.dist-info/LICENSE
netifaces_w38-0.10.9.dist-info/METADATA
netifaces_w38-0.10.9.dist-info/WHEEL
netifaces_w38-0.10.9.dist-info/top_level.txt
netifaces_w38-0.10.9.dist-info/zip-safe
netifaces_w38-0.10.9.dist-info/RECORD
